[{"grammar": {"partofs": "adjective"}, "ohne": "iki", "word": "iki", "uebersetzungen": {"ru": "два", "en": "two", "de": "zwei", "ko": "2", "ar": "اثنين", "he": "שני"}}, {"grammar": {"partofs": "noun"}, "ohne": "du", "word": "du", "uebersetzungen": {"ru": "Du", "en": "du", "de": "Du", "ko": "뒤", "ar": "دو", "he": "du"}}, {"grammar": {"gender": "female", "partofs": "noun"}, "ohne": "Maus", "word": "Maus", "uebersetzungen": {"ru": "Maus", "en": "Maus", "de": "Maus", "ko": "Maus", "ar": "موس", "he": "\"מאוס\""}}, {"grammar": {"gender": "neuter", "partofs": "noun"}, "ohne": "Eichhornchen", "word": "Eichhörnchen", "uebersetzungen": {"ru": "Eichhörnchen", "en": "Eichhörnchen", "de": "Eichhörnchen", "ko": "Eichhörnchen", "ar": "Eichhörnchen", "he": "Eichhörnchen"}}, {"grammar": {"partofs": "verb"}, "ohne": "gemacht", "word": "gemacht", "uebersetzungen": {"ru": "gemacht", "en": "gemacht", "de": "gemacht", "ko": "에", "ar": "gemacht", "he": "gemacht"}}, {"grammar": {"partofs": "noun", "number": "plural"}, "ohne": "Zwiebeln", "word": "Zwiebeln", "uebersetzungen": {"ru": "Zwiebeln", "en": "Zwiebeln", "de": "Zwiebeln", "ko": "Zwiebeln", "ar": "زويبيلن", "he": "Zwiebeln"}}, {"grammar": {"partofs": "verb"}, "ohne": "tschuss", "word": "tschüss", "uebersetzungen": {"ru": "tschüss", "en": "tschüss", "de": "Tschüss", "ko": "tschüss", "ar": "tschüss", "he": "tschüss"}}, {"grammar": {"partofs": "adjective"}, "ohne": "zwei", "word": "zwei", "uebersetzungen": {"ru": "Zwei", "en": "zwei", "de": "zwei", "ko": "zwei", "ar": "zwei", "he": "zwei"}}, {"grammar": {"gender": "female", "partofs": "noun"}, "ohne": "Straße", "word": "Straße", "uebersetzungen": {"ru": "Штрассе", "en": "Straße", "de": "Straße", "ko": "스 트 라 세", "ar": "Straße", "he": "שטראסה (straße)"}}, {"grammar": {"partofs": "noun", "number": "plural"}, "ohne": "Karten", "word": "Karten", "uebersetzungen": {"ru": "Картинг", "en": "Go kart", "de": "Go-Kart", "ko": "이동 카트", "ar": "يذهب كارت", "he": "מעבר kart"}}, {"grammar": {"partofs": "verb"}, "ohne": "mochte", "word": "möchte", "uebersetzungen": {"ru": "mädel.möchte как", "en": "mädel.möchte like", "de": "Mädel.möchte wie", "ko": "같은 mädel.möchte", "ar": "mädel.möchte مثل", "he": "mädel.möchte כמו"}}, {"grammar": {"partofs": "verb"}, "ohne": "hatte", "word": "hätte", "uebersetzungen": {"ru": "hätte", "en": "hätte", "de": "hätte", "ko": "hätte", "ar": "أود", "he": "hätte"}}, {"grammar": {"partofs": "verb"}, "ohne": "hatte", "word": "hatte", "uebersetzungen": {"ru": "Hatte", "en": "hatte", "de": "hatte", "ko": "hatte", "ar": "هات", "he": "hatte"}}, {"grammar": {"partofs": "adjective"}, "ohne": "nein", "word": "nein", "uebersetzungen": {"ru": "Найн", "en": "Nein", "de": "Nein", "ko": "아냐", "ar": "نين", "he": "לא"}}, {"grammar": {"partofs": "noun"}, "ohne": "Munchen", "word": "München", "uebersetzungen": {"ru": "Мюнхен", "en": "München", "de": "München", "ko": "뮌헨", "ar": "ميونيخ", "he": "מינכן"}}, {"grammar": {"partofs": "noun"}, "ohne": "Angela", "word": "Angela", "uebersetzungen": {"ru": "Анжела", "en": "Angela", "de": "Angela", "ko": "안젤라", "ar": "أنجيلا", "he": "אנג'לה"}}, {"grammar": {"partofs": "noun"}, "ohne": "Merkel", "word": "Merkel", "uebersetzungen": {"ru": "Меркель", "en": "Merkel", "de": "Merkel", "ko": "메르켈 총리", "ar": "ميركل", "he": "מרקל"}}, {"grammar": {"partofs": "noun"}, "ohne": "was", "word": "was", "uebersetzungen": {"ru": "был", "en": "was", "de": "war", "ko": "했다", "ar": "وكان", "he": "היה"}}, {"grammar": {"gender": "female", "partofs": "noun", "number": "singular"}, "ohne": "Chance", "word": "Chance", "uebersetzungen": {"ru": "Шанс", "en": "Chance", "de": "Chance", "ko": "기회", "ar": "فرصة", "he": "הזדמנות"}}, {"grammar": {"gender": "male", "partofs": "noun"}, "ohne": "Tee", "word": "Tee", "uebersetzungen": {"ru": "Тройник", "en": "Tee", "de": "Tee", "ko": "티", "ar": "كوم", "he": "טי"}}, {"grammar": {"gender": "neuter", "partofs": "noun"}, "ohne": "Pferd", "word": "Pferd", "uebersetzungen": {"ru": "PFERD", "en": "Pferd", "de": "Pferd", "ko": "가슴", "ar": "فرد", "he": "Pferd"}}, {"grammar": {"partofs": "adjective"}, "ohne": "naturlich", "word": "natürlich", "uebersetzungen": {"ru": "Na türlich", "en": "na türlich", "de": "Na dunz.Jurgen", "ko": "na türlich", "ar": "türlich نا", "he": "נה türlich"}}, {"grammar": {"gender": "male", "partofs": "noun"}, "ohne": "Saft", "word": "Saft", "uebersetzungen": {"ru": "SAFT", "en": "SAFT", "de": "SAFT", "ko": "SAFT", "ar": "صفط", "he": "זפט"}}]